{
  "baseUrl": "http://127.0.0.1:8652",
  "runtimeMode": "spawned",
  "targetTrades": 1,
  "reachedTarget": false,
  "elapsedMs": 60145,
  "maxWaitMs": 60000,
  "gateTimeoutMs": 86400000,
  "runtimeGateStale": false,
  "gate": {
    "passed": false,
    "reason": "awaiting_trades",
    "tier": 1,
    "currentTier": 0,
    "trades": 0,
    "elapsedMs": 60061,
    "kpi": {
      "tradesPerMinute": 0,
      "profitFactor": 0,
      "netPnlUsd": 0,
      "maxDrawdownPct": 0
    },
    "limits": {
      "maxTradesPerMinute": 4,
      "minProfitFactor": 0,
      "minNetPnlUsd": -0.75,
      "maxDrawdownPct": 0.05,
      "timeoutMs": 86400000
    }
  },
  "paperSanity": {
    "passed": true,
    "reason": "not evaluated",
    "netPnlUsd": 0,
    "maxDrawdownPct": 0,
    "criticalAlertsCount": 0
  },
  "overallPassed": false,
  "alertWindow": {
    "startMs": 1772476990798,
    "endMs": 1772477050949,
    "startIso": "2026-03-02T18:43:10.798Z",
    "endIso": "2026-03-02T18:44:10.949Z"
  },
  "criticalAlerts": [],
  "final": {
    "ts": "2026-03-02T18:44:10.943Z",
    "rlTrades": 0,
    "rlWinRate": 0,
    "rlProfitFactor": 0,
    "rlNetPnlUsd": 0,
    "rlMaxDrawdownPct": 0,
    "rlQGapStats": null,
    "rlRegimeStats": null,
    "runtimeStage": "paper",
    "runtimePaperTrades": 0,
    "runtimePaperProfitFactor": 0
  },
  "guardBlocks": {
    "confidence": 0,
    "minHold": 0,
    "flipCooldown": 0,
    "lowStrength": 0,
    "confidenceTriggered": 0,
    "total": 0,
    "actionsBeforeGuards": 0,
    "actionsAfterGuards": 0,
    "confidenceGateEnabled": true,
    "confidenceQGap": 0.01,
    "effectiveConfidenceQGap": 0.0034999999999999996,
    "confidenceQGapAdaptiveEnabled": true,
    "confidenceQGapAdaptiveQuantile": 0.6,
    "confidenceQGapAdaptiveScale": 0.8,
    "confidenceQGapMin": 0.0008,
    "minSignalStrength": 0
  },
  "sampleStats": {
    "firstTradeTs": null,
    "firstTradeRlTrades": null,
    "maxObservedDrawdownPct": 0,
    "minObservedNetPnlUsd": 0,
    "maxObservedNetPnlUsd": 0,
    "elapsedMinutes": 0.9522833333333334,
    "tradesPerMinute": 0
  },
  "samplesCount": 20,
  "lastSamples": [
    {
      "ts": "2026-03-02T18:43:55.914Z",
      "rlTrades": 0,
      "rlWinRate": 0,
      "rlProfitFactor": 0,
      "rlNetPnlUsd": 0,
      "rlMaxDrawdownPct": 0,
      "rlQGapStats": null,
      "rlRegimeStats": null,
      "runtimeStage": "paper",
      "runtimePaperTrades": 0,
      "runtimePaperProfitFactor": 0
    },
    {
      "ts": "2026-03-02T18:43:58.918Z",
      "rlTrades": 0,
      "rlWinRate": 0,
      "rlProfitFactor": 0,
      "rlNetPnlUsd": 0,
      "rlMaxDrawdownPct": 0,
      "rlQGapStats": null,
      "rlRegimeStats": null,
      "runtimeStage": "paper",
      "runtimePaperTrades": 0,
      "runtimePaperProfitFactor": 0
    },
    {
      "ts": "2026-03-02T18:44:01.921Z",
      "rlTrades": 0,
      "rlWinRate": 0,
      "rlProfitFactor": 0,
      "rlNetPnlUsd": 0,
      "rlMaxDrawdownPct": 0,
      "rlQGapStats": null,
      "rlRegimeStats": null,
      "runtimeStage": "paper",
      "runtimePaperTrades": 0,
      "runtimePaperProfitFactor": 0
    },
    {
      "ts": "2026-03-02T18:44:04.928Z",
      "rlTrades": 0,
      "rlWinRate": 0,
      "rlProfitFactor": 0,
      "rlNetPnlUsd": 0,
      "rlMaxDrawdownPct": 0,
      "rlQGapStats": null,
      "rlRegimeStats": null,
      "runtimeStage": "paper",
      "runtimePaperTrades": 0,
      "runtimePaperProfitFactor": 0
    },
    {
      "ts": "2026-03-02T18:44:07.940Z",
      "rlTrades": 0,
      "rlWinRate": 0,
      "rlProfitFactor": 0,
      "rlNetPnlUsd": 0,
      "rlMaxDrawdownPct": 0,
      "rlQGapStats": null,
      "rlRegimeStats": null,
      "runtimeStage": "paper",
      "runtimePaperTrades": 0,
      "runtimePaperProfitFactor": 0
    }
  ],
  "runtimeData": {
    "alertsCount": 0,
    "auditEventsCount": 54,
    "fillsCount": 0,
    "ordersCount": 0,
    "equityPoints": 2,
    "alertsTail": [],
    "auditTail": [
      {
        "ts": 1772477013096,
        "type": "signal_generated",
        "severity": null,
        "symbol": null,
        "detail": null
      },
      {
        "ts": 1772477013093,
        "type": "signal_generated",
        "severity": null,
        "symbol": null,
        "detail": null
      },
      {
        "ts": 1772477011252,
        "type": "signal_generated",
        "severity": null,
        "symbol": null,
        "detail": null
      },
      {
        "ts": 1772477011249,
        "type": "signal_generated",
        "severity": null,
        "symbol": null,
        "detail": null
      },
      {
        "ts": 1772477009218,
        "type": "signal_generated",
        "severity": null,
        "symbol": null,
        "detail": null
      },
      {
        "ts": 1772477009214,
        "type": "signal_generated",
        "severity": null,
        "symbol": null,
        "detail": null
      },
      {
        "ts": 1772477007106,
        "type": "signal_generated",
        "severity": null,
        "symbol": null,
        "detail": null
      },
      {
        "ts": 1772477007102,
        "type": "signal_generated",
        "severity": null,
        "symbol": null,
        "detail": null
      },
      {
        "ts": 1772477005094,
        "type": "signal_generated",
        "severity": null,
        "symbol": null,
        "detail": null
      },
      {
        "ts": 1772477003177,
        "type": "signal_generated",
        "severity": null,
        "symbol": null,
        "detail": null
      },
      {
        "ts": 1772477003172,
        "type": "signal_generated",
        "severity": null,
        "symbol": null,
        "detail": null
      },
      {
        "ts": 1772477001120,
        "type": "signal_generated",
        "severity": null,
        "symbol": null,
        "detail": null
      },
      {
        "ts": 1772477001116,
        "type": "signal_generated",
        "severity": null,
        "symbol": null,
        "detail": null
      },
      {
        "ts": 1772476999104,
        "type": "signal_generated",
        "severity": null,
        "symbol": null,
        "detail": null
      },
      {
        "ts": 1772476999100,
        "type": "signal_generated",
        "severity": null,
        "symbol": null,
        "detail": null
      },
      {
        "ts": 1772476997098,
        "type": "signal_generated",
        "severity": null,
        "symbol": null,
        "detail": null
      },
      {
        "ts": 1772476995125,
        "type": "signal_generated",
        "severity": null,
        "symbol": null,
        "detail": null
      },
      {
        "ts": 1772476995121,
        "type": "signal_generated",
        "severity": null,
        "symbol": null,
        "detail": null
      },
      {
        "ts": 1772476993217,
        "type": "signal_generated",
        "severity": null,
        "symbol": null,
        "detail": null
      },
      {
        "ts": 1772476993214,
        "type": "signal_generated",
        "severity": null,
        "symbol": null,
        "detail": null
      }
    ]
  },
  "finalSnapshots": {
    "rlStatus": {
      "enabled": true,
      "modelKind": "rl_linear_q",
      "initialCapitalUsd": 10000,
      "equityUsd": 10000,
      "netPnlUsd": 0,
      "totalCostsUsd": 0,
      "maxDrawdownPct": 0,
      "trades": 0,
      "tradesPerMinute": 0,
      "startedAt": 1772476990606,
      "elapsedMs": 60340,
      "firstTradeTs": null,
      "lastTradeTs": null,
      "winRate": 0,
      "profitFactor": 0,
      "qGapStats": null,
      "regimeStats": null,
      "symbols": [
        "BTCUSDT",
        "ETHUSDT"
      ],
      "openPositions": [],
      "guardBlocks": {
        "confidence": 0,
        "minHold": 0,
        "flipCooldown": 0,
        "lowStrength": 0,
        "confidenceTriggered": 0,
        "total": 0,
        "actionsBeforeGuards": 0,
        "actionsAfterGuards": 0,
        "confidenceGateEnabled": true,
        "confidenceQGap": 0.01,
        "effectiveConfidenceQGap": 0.0034999999999999996,
        "confidenceQGapAdaptiveEnabled": true,
        "confidenceQGapAdaptiveQuantile": 0.6,
        "confidenceQGapAdaptiveScale": 0.8,
        "confidenceQGapMin": 0.0008,
        "minSignalStrength": 0
      }
    },
    "runtimeStatus": {
      "stage": "paper",
      "killSwitch": {
        "enabled": false,
        "reason": ""
      },
      "cashUsd": 10000,
      "equityUsd": 10000,
      "realizedPnlUsd": 0,
      "unrealizedPnlUsd": 0,
      "drawdownPct": 0,
      "paperMetrics": {
        "trades": 0,
        "wins": 0,
        "losses": 0,
        "grossProfitUsd": 0,
        "grossLossUsd": 0,
        "netPnlUsd": 0,
        "maxDrawdownPct": 0,
        "winRate": 0,
        "profitFactor": 0
      },
      "tinyLiveRiskMultiplier": 0.1,
      "paperSanity": {
        "passed": true,
        "reason": "not evaluated",
        "netPnlUsd": 0,
        "maxDrawdownPct": 0,
        "criticalAlertsCount": 0
      },
      "backtestGate": {
        "passed": false,
        "reason": "failed gate (profitFactor/drawdown)"
      },
      "shadowGate": {
        "passed": false,
        "reason": "awaiting_trades",
        "tier": 1,
        "currentTier": 0,
        "trades": 0,
        "elapsedMs": 60061,
        "kpi": {
          "tradesPerMinute": 0,
          "profitFactor": 0,
          "netPnlUsd": 0,
          "maxDrawdownPct": 0
        },
        "limits": {
          "maxTradesPerMinute": 4,
          "minProfitFactor": 0,
          "minNetPnlUsd": -0.75,
          "maxDrawdownPct": 0.05,
          "timeoutMs": 86400000
        }
      },
      "rlExecutionGuards": {
        "confidence": 0,
        "minHold": 0,
        "flipCooldown": 0,
        "lowStrength": 0,
        "confidenceTriggered": 0,
        "actionsBeforeGuards": 0,
        "actionsAfterGuards": 0,
        "confidenceGateEnabled": true,
        "confidenceQGap": 0.01,
        "effectiveConfidenceQGap": 0.0034999999999999996,
        "confidenceQGapAdaptiveEnabled": true,
        "confidenceQGapAdaptiveQuantile": 0.6,
        "confidenceQGapAdaptiveScale": 0.8,
        "confidenceQGapMin": 0.0008,
        "minSignalStrength": 0,
        "holdFlattenEnabled": false,
        "minHoldBars": 3,
        "flipCooldownBars": 1,
        "maxPositionBars": 6
      },
      "lossStreakCooldown": {
        "active": false,
        "remainingMs": 0,
        "recentLossStreak": 0,
        "streakThreshold": 0,
        "cooldownMinutes": 0
      },
      "recentAlerts": []
    }
  }
}