{
  "baseUrl": "http://127.0.0.1:8652",
  "runtimeMode": "spawned",
  "targetTrades": 1,
  "reachedTarget": false,
  "elapsedMs": 120368,
  "maxWaitMs": 120000,
  "gateTimeoutMs": 86400000,
  "runtimeGateStale": false,
  "gate": {
    "passed": false,
    "reason": "kpi_fail",
    "tier": 1,
    "currentTier": 0,
    "trades": 1,
    "elapsedMs": 341,
    "kpi": {
      "tradesPerMinute": 175.95307917888562,
      "profitFactor": 50,
      "netPnlUsd": -0.27000280017455225,
      "maxDrawdownPct": 0.0027000280017455227
    },
    "limits": {
      "maxTradesPerMinute": 4,
      "minProfitFactor": 0,
      "minNetPnlUsd": -0.5,
      "maxDrawdownPct": 0.05,
      "timeoutMs": 86400000
    }
  },
  "paperSanity": {
    "passed": true,
    "reason": "ok",
    "netPnlUsd": -0.34337174820800015,
    "maxDrawdownPct": 0.003433717482075736,
    "criticalAlertsCount": 0
  },
  "overallPassed": false,
  "alertWindow": {
    "startMs": 1772471513641,
    "endMs": 1772471634015,
    "startIso": "2026-03-02T17:11:53.641Z",
    "endIso": "2026-03-02T17:13:54.015Z"
  },
  "criticalAlerts": [],
  "final": {
    "ts": "2026-03-02T17:13:54.009Z",
    "rlTrades": 0,
    "rlWinRate": 0,
    "rlProfitFactor": 0,
    "rlNetPnlUsd": -0.24337638648648863,
    "rlMaxDrawdownPct": 0.002433763864864886,
    "rlQGapStats": {
      "p50": 0.0007393947158253616,
      "p75": 0.0017914748828324611,
      "p90": 0.0029732466655649353
    },
    "rlRegimeStats": null,
    "runtimeStage": "paper",
    "runtimePaperTrades": 3,
    "runtimePaperProfitFactor": 0
  },
  "guardBlocks": {
    "confidence": 18,
    "minHold": 0,
    "flipCooldown": 0,
    "lowStrength": 0,
    "confidenceTriggered": 18,
    "total": 18,
    "actionsBeforeGuards": 23,
    "actionsAfterGuards": 3,
    "confidenceGateEnabled": true,
    "confidenceQGap": 0.012,
    "effectiveConfidenceQGap": 0.0008,
    "confidenceQGapAdaptiveEnabled": true,
    "confidenceQGapAdaptiveQuantile": 0.55,
    "confidenceQGapAdaptiveScale": 0.8,
    "confidenceQGapMin": 0.0008,
    "minSignalStrength": 0
  },
  "sampleStats": {
    "firstTradeTs": null,
    "firstTradeRlTrades": null,
    "maxObservedDrawdownPct": 0.0027132242461811984,
    "minObservedNetPnlUsd": -0.27132242461811984,
    "maxObservedNetPnlUsd": 0,
    "elapsedMinutes": 1.9558833333333334,
    "tradesPerMinute": 0
  },
  "samplesCount": 40,
  "lastSamples": [
    {
      "ts": "2026-03-02T17:13:38.978Z",
      "rlTrades": 0,
      "rlWinRate": 0,
      "rlProfitFactor": 0,
      "rlNetPnlUsd": 0,
      "rlMaxDrawdownPct": 0,
      "rlQGapStats": {
        "p50": 0.0004015600380714718,
        "p75": 0.0007393947158253616,
        "p90": 0.001061830362170349
      },
      "rlRegimeStats": null,
      "runtimeStage": "paper",
      "runtimePaperTrades": 1,
      "runtimePaperProfitFactor": 0
    },
    {
      "ts": "2026-03-02T17:13:41.988Z",
      "rlTrades": 0,
      "rlWinRate": 0,
      "rlProfitFactor": 0,
      "rlNetPnlUsd": -0.24873277310689446,
      "rlMaxDrawdownPct": 0.0024873277310689446,
      "rlQGapStats": {
        "p50": 0.0005014717965364929,
        "p75": 0.001061830362170349,
        "p90": 0.001629604406558821
      },
      "rlRegimeStats": null,
      "runtimeStage": "paper",
      "runtimePaperTrades": 2,
      "runtimePaperProfitFactor": 0
    },
    {
      "ts": "2026-03-02T17:13:44.991Z",
      "rlTrades": 0,
      "rlWinRate": 0,
      "rlProfitFactor": 0,
      "rlNetPnlUsd": -0.24581339299038518,
      "rlMaxDrawdownPct": 0.0024581339299038518,
      "rlQGapStats": {
        "p50": 0.0005907684040544064,
        "p75": 0.0012438476986568747,
        "p90": 0.0019165218033658782
      },
      "rlRegimeStats": null,
      "runtimeStage": "paper",
      "runtimePaperTrades": 2,
      "runtimePaperProfitFactor": 0
    },
    {
      "ts": "2026-03-02T17:13:47.994Z",
      "rlTrades": 0,
      "rlWinRate": 0,
      "rlProfitFactor": 0,
      "rlNetPnlUsd": -0.27132242461811984,
      "rlMaxDrawdownPct": 0.0027132242461811984,
      "rlQGapStats": {
        "p50": 0.0007285441658768099,
        "p75": 0.001629604406558821,
        "p90": 0.0023119630328392454
      },
      "rlRegimeStats": null,
      "runtimeStage": "paper",
      "runtimePaperTrades": 2,
      "runtimePaperProfitFactor": 0
    },
    {
      "ts": "2026-03-02T17:13:50.999Z",
      "rlTrades": 0,
      "rlWinRate": 0,
      "rlProfitFactor": 0,
      "rlNetPnlUsd": -0.24337638648648863,
      "rlMaxDrawdownPct": 0.002433763864864886,
      "rlQGapStats": {
        "p50": 0.0007393947158253616,
        "p75": 0.0017914748828324611,
        "p90": 0.0029732466655649353
      },
      "rlRegimeStats": null,
      "runtimeStage": "paper",
      "runtimePaperTrades": 3,
      "runtimePaperProfitFactor": 0
    }
  ],
  "runtimeData": {
    "alertsCount": 0,
    "auditEventsCount": 151,
    "fillsCount": 9,
    "ordersCount": 5,
    "equityPoints": 3,
    "alertsTail": [],
    "auditTail": [
      {
        "ts": 1772471535138,
        "type": "signal_generated",
        "severity": null,
        "symbol": null,
        "detail": null
      },
      {
        "ts": 1772471535135,
        "type": "signal_generated",
        "severity": null,
        "symbol": null,
        "detail": null
      },
      {
        "ts": 1772471533118,
        "type": "signal_generated",
        "severity": null,
        "symbol": null,
        "detail": null
      },
      {
        "ts": 1772471533114,
        "type": "signal_generated",
        "severity": null,
        "symbol": null,
        "detail": null
      },
      {
        "ts": 1772471531114,
        "type": "signal_generated",
        "severity": null,
        "symbol": null,
        "detail": null
      },
      {
        "ts": 1772471531111,
        "type": "signal_generated",
        "severity": null,
        "symbol": null,
        "detail": null
      },
      {
        "ts": 1772471529219,
        "type": "signal_generated",
        "severity": null,
        "symbol": null,
        "detail": null
      },
      {
        "ts": 1772471529216,
        "type": "signal_generated",
        "severity": null,
        "symbol": null,
        "detail": null
      },
      {
        "ts": 1772471527742,
        "type": "signal_generated",
        "severity": null,
        "symbol": null,
        "detail": null
      },
      {
        "ts": 1772471527739,
        "type": "signal_generated",
        "severity": null,
        "symbol": null,
        "detail": null
      },
      {
        "ts": 1772471525130,
        "type": "signal_generated",
        "severity": null,
        "symbol": null,
        "detail": null
      },
      {
        "ts": 1772471525127,
        "type": "signal_generated",
        "severity": null,
        "symbol": null,
        "detail": null
      },
      {
        "ts": 1772471523130,
        "type": "signal_generated",
        "severity": null,
        "symbol": null,
        "detail": null
      },
      {
        "ts": 1772471523127,
        "type": "signal_generated",
        "severity": null,
        "symbol": null,
        "detail": null
      },
      {
        "ts": 1772471521136,
        "type": "signal_generated",
        "severity": null,
        "symbol": null,
        "detail": null
      },
      {
        "ts": 1772471521133,
        "type": "signal_generated",
        "severity": null,
        "symbol": null,
        "detail": null
      },
      {
        "ts": 1772471519110,
        "type": "signal_generated",
        "severity": null,
        "symbol": null,
        "detail": null
      },
      {
        "ts": 1772471519106,
        "type": "signal_generated",
        "severity": null,
        "symbol": null,
        "detail": null
      },
      {
        "ts": 1772471517273,
        "type": "signal_generated",
        "severity": null,
        "symbol": null,
        "detail": null
      },
      {
        "ts": 1772471517270,
        "type": "signal_generated",
        "severity": null,
        "symbol": null,
        "detail": null
      }
    ]
  },
  "finalSnapshots": {
    "rlStatus": {
      "enabled": true,
      "modelKind": "rl_linear_q",
      "initialCapitalUsd": 10000,
      "equityUsd": 9999.729997199825,
      "netPnlUsd": -0.27000280017455225,
      "totalCostsUsd": 0.27521212466903133,
      "maxDrawdownPct": 0.0027000280017455227,
      "trades": 1,
      "tradesPerMinute": 66.66666666666667,
      "startedAt": 1772471513395,
      "elapsedMs": 900,
      "firstTradeTs": 1772471633113,
      "lastTradeTs": 1772471633113,
      "winRate": 1,
      "profitFactor": 50,
      "qGapStats": {
        "p50": 0.0007958973296609134,
        "p75": 0.0017834876381937759,
        "p90": 0.0029732466655649353
      },
      "regimeStats": null,
      "symbols": [
        "BTCUSDT",
        "ETHUSDT"
      ],
      "openPositions": [
        {
          "symbol": "BTCUSDT",
          "side": "long",
          "entryPrice": 69381.99,
          "entryTs": 1772471580000
        }
      ],
      "guardBlocks": {
        "confidence": 18,
        "minHold": 0,
        "flipCooldown": 0,
        "lowStrength": 0,
        "confidenceTriggered": 18,
        "total": 18,
        "actionsBeforeGuards": 23,
        "actionsAfterGuards": 3,
        "confidenceGateEnabled": true,
        "confidenceQGap": 0.012,
        "effectiveConfidenceQGap": 0.0008,
        "confidenceQGapAdaptiveEnabled": true,
        "confidenceQGapAdaptiveQuantile": 0.55,
        "confidenceQGapAdaptiveScale": 0.8,
        "confidenceQGapMin": 0.0008,
        "minSignalStrength": 0
      }
    },
    "runtimeStatus": {
      "stage": "paper",
      "killSwitch": {
        "enabled": false,
        "reason": ""
      },
      "cashUsd": 9959.656940411793,
      "equityUsd": 9999.669863771793,
      "realizedPnlUsd": -0.34337174820800015,
      "unrealizedPnlUsd": 0.003308880000001416,
      "drawdownPct": 0.0033013622820726595,
      "paperMetrics": {
        "trades": 5,
        "wins": 0,
        "losses": 5,
        "grossProfitUsd": 0,
        "grossLossUsd": 0.34337174820800015,
        "netPnlUsd": -0.34337174820800015,
        "maxDrawdownPct": 0.003433717482075736,
        "winRate": 0,
        "profitFactor": 0
      },
      "tinyLiveRiskMultiplier": 0.1,
      "paperSanity": {
        "passed": true,
        "reason": "ok",
        "netPnlUsd": -0.34337174820800015,
        "maxDrawdownPct": 0.003433717482075736,
        "criticalAlertsCount": 0
      },
      "backtestGate": {
        "passed": false,
        "reason": "failed gate (profitFactor/drawdown)"
      },
      "shadowGate": {
        "passed": false,
        "reason": "kpi_fail",
        "tier": 1,
        "currentTier": 0,
        "trades": 1,
        "elapsedMs": 341,
        "kpi": {
          "tradesPerMinute": 175.95307917888562,
          "profitFactor": 50,
          "netPnlUsd": -0.27000280017455225,
          "maxDrawdownPct": 0.0027000280017455227
        },
        "limits": {
          "maxTradesPerMinute": 4,
          "minProfitFactor": 0,
          "minNetPnlUsd": -0.5,
          "maxDrawdownPct": 0.05,
          "timeoutMs": 86400000
        }
      },
      "rlExecutionGuards": {
        "confidence": 18,
        "minHold": 0,
        "flipCooldown": 0,
        "lowStrength": 0,
        "confidenceTriggered": 18,
        "actionsBeforeGuards": 21,
        "actionsAfterGuards": 3,
        "confidenceGateEnabled": true,
        "confidenceQGap": 0.012,
        "effectiveConfidenceQGap": 0.0008,
        "confidenceQGapAdaptiveEnabled": true,
        "confidenceQGapAdaptiveQuantile": 0.55,
        "confidenceQGapAdaptiveScale": 0.8,
        "confidenceQGapMin": 0.0008,
        "minSignalStrength": 0,
        "holdFlattenEnabled": false,
        "minHoldBars": 3,
        "flipCooldownBars": 1,
        "maxPositionBars": 6
      },
      "lossStreakCooldown": {
        "active": false,
        "remainingMs": 0,
        "recentLossStreak": 5,
        "streakThreshold": 0,
        "cooldownMinutes": 0
      },
      "recentAlerts": []
    }
  }
}